systemair/__init__.py
systemair/savecair/__init__.py
systemair/savecair/command.py
systemair/savecair/const.py
systemair/savecair/systemair.py
python_systemair_savecair-2.0.1.dist-info/LICENSE.txt
python_systemair_savecair-2.0.1.dist-info/METADATA
python_systemair_savecair-2.0.1.dist-info/WHEEL
python_systemair_savecair-2.0.1.dist-info/top_level.txt
python_systemair_savecair-2.0.1.dist-info/RECORD
