Metadata-Version: 2.1
Name: python-systemair-savecair
Version: 2.0.1
Summary: A Systemair-savecair API Wrapper
Home-page: https://github.com/perara/python-systemair-savecair
Author: Per-Arne Andersen
Author-email: per@sysx.no
License: MIT
Platform: UNKNOWN
Classifier: Programming Language :: Python :: 3
Classifier: License :: OSI Approved :: MIT License
Classifier: Operating System :: OS Independent
Requires-Dist: websockets (==8.1)
